{
    "title": "Char-Broil Hair Dryer Commercial (2013)",
    "description": "How TRU-Infrared Works The science behind TRU-Infrared tells a juicy story. Unlike traditional gas grills that use convective heat (hot air) to cook food, Ch...",
    "referenceId": null,
    "date_created": "1382373058",
    "date_modified": "1418181068",
    "tags": "",
    "sourceId": "4",
    "VIDEO_LENGTH": "SHORT",
    "status": "approved",
    "visibility": "1",
    "id": "125124",
    "loginId": "521",
    "entityType": "1",
    "titleTextEncoded": "Char-Broil-Hair-Dryer-Commercial-2013",
    "category": null,
    "duration": 17,
    "settings": [],
    "asset": {
        "author": "charbroil",
        "videoId": "UneLQNGsYBI",
        "hookText": "How TRU-Infrared Works The science behind TRU-Infrared tells a juicy story. Unlike traditional gas grills that use convective heat (hot air) to cook food, Ch...",
        "thumbnailUrl": "https:\/\/i.ytimg.com\/vi\/UneLQNGsYBI\/mqdefault.jpg",
        "mediaDuration": "17",
        "hdvFlag": 1,
        "uploadDate": 1374092285,
        "prettyDuration": "00:17"
    },
    "transcripts": null,
    "VV_VI": null,
    "CVV_VI": null,
    "engagement_score": null,
    "conversion_score": null,
    "metrics_statistics": null,
    "tvp_profiles": [
        "14"
    ],
    "tvp_profiles_manual": null,
    "tvp_profiles_maxscore": 378.06152
}