{
    "title": "Steren Comercial Golf",
    "description": "Steren Soluciones s\u00f3lo en electr\u00f3nica Mira lo que sucede cuando el mexicano gana su primer torneo profesional de golf. http:\/\/www.steren.com.mx\/",
    "referenceId": null,
    "date_created": "1385165255",
    "date_modified": "1418181112",
    "tags": "",
    "sourceId": "4",
    "VIDEO_LENGTH": "SHORT",
    "status": "approved",
    "visibility": "1",
    "id": "134077",
    "loginId": "521",
    "entityType": "1",
    "titleTextEncoded": "Steren-Comercial-Golf",
    "category": null,
    "duration": 54,
    "settings": [],
    "asset": {
        "author": "STERENMEDIA",
        "videoId": "8flp_V4ggZY",
        "hookText": "Steren Soluciones s\u00f3lo en electr\u00f3nica Mira lo que sucede cuando el mexicano gana su primer torneo profesional de golf. http:\/\/www.steren.com.mx\/",
        "thumbnailUrl": "https:\/\/i.ytimg.com\/vi\/8flp_V4ggZY\/maxresdefault.jpg",
        "mediaDuration": "54",
        "hdvFlag": 1,
        "uploadDate": 1378248374,
        "prettyDuration": "00:54"
    },
    "transcripts": null,
    "VV_VI": null,
    "CVV_VI": null,
    "engagement_score": null,
    "conversion_score": null,
    "metrics_statistics": null,
    "tvp_profiles": [
        "25"
    ],
    "tvp_profiles_manual": null,
    "tvp_profiles_maxscore": 99.44427
}