{
    "title": "Jockey by Design: Women's Cheeky Modal & Microfiber Underwea",
    "description": "Cheeky women's underwear offer a feminine fit and stylish look. Bright colors and fashionable prints are perfect to complement your favorite look. Available in microfiber with lace and modal with picot trim.\n\nReady to find your favorite? Get started at Jo",
    "referenceId": null,
    "date_created": "1386970486",
    "date_modified": "1418181129",
    "tags": "",
    "sourceId": "4",
    "VIDEO_LENGTH": "SHORT",
    "status": "approved",
    "visibility": "1",
    "id": "136180",
    "loginId": "521",
    "entityType": "1",
    "titleTextEncoded": "Jockey-by-Design-Women-s-Cheeky-Modal-Microfiber-Underwea",
    "category": null,
    "duration": 66,
    "settings": [],
    "asset": {
        "author": "Jockey",
        "hdvFlag": 1,
        "mediaDuration": "66",
        "thumbnailUrl": "https:\/\/i1.ytimg.com\/vi\/AhK2AQKUWEQ\/mqdefault.jpg",
        "uploadDate": 1345474544,
        "videoId": "AhK2AQKUWEQ",
        "hookText": "Cheeky women's underwear offer a feminine fit and stylish look. Bright colors and fashionable prints are perfect to complement your favorite look. Available in microfiber with lace and modal with picot trim.\n\nReady to find your favorite? Get started at Jockey.com."
    },
    "transcripts": null,
    "VV_VI": null,
    "CVV_VI": null,
    "engagement_score": null,
    "conversion_score": null,
    "metrics_statistics": null,
    "tvp_profiles": [
        "28",
        "18",
        "11"
    ],
    "tvp_profiles_manual": null,
    "tvp_profiles_maxscore": 599.4578
}