{
    "title": "Exercise Ball Workout with Professional Fitness Trainer",
    "description": "Join Everlast's professional fitness trainer Viktoria Telek as she goes through core workout techniques using an exercise fitness ball.\nMore how-to videos can be seen here: http:\/\/www.everlast.com\/educationcenter\nExercise Fitness Balls can be purchased he",
    "referenceId": null,
    "date_created": "1387302681",
    "date_modified": "1418181132",
    "tags": "",
    "sourceId": "4",
    "VIDEO_LENGTH": "SHORT",
    "status": "approved",
    "visibility": "1",
    "id": "136649",
    "loginId": "521",
    "entityType": "1",
    "titleTextEncoded": "Exercise-Ball-Workout-with-Professional-Fitness-Trainer",
    "category": null,
    "duration": 64,
    "settings": [],
    "asset": {
        "author": "Everlast",
        "hdvFlag": 1,
        "mediaDuration": "64",
        "thumbnailUrl": "https:\/\/i.ytimg.com\/vi\/MBuE230VcKQ\/mqdefault.jpg",
        "uploadDate": 1374675255,
        "videoId": "MBuE230VcKQ",
        "hookText": "Join Everlast's professional fitness trainer Viktoria Telek as she goes through core workout techniques using an exercise fitness ball.\nMore how-to videos can be seen here: http:\/\/www.everlast.com\/educationcenter\nExercise Fitness Balls can be purchased here: http:\/\/www.shopeverlast.com\/inflatible-ball-pump.html"
    },
    "transcripts": null,
    "VV_VI": null,
    "CVV_VI": null,
    "engagement_score": null,
    "conversion_score": null,
    "metrics_statistics": null,
    "tvp_profiles": [
        "25"
    ],
    "tvp_profiles_manual": null,
    "tvp_profiles_maxscore": 599.4551
}