{
    "title": "Zoo Med Tortoise House",
    "description": "http:\/\/video.petco.com\/?v=26346 View this video featuring the Zoo Med Tortoise House product and shop other similar products on petco.com. More information [...",
    "referenceId": null,
    "date_created": "1394588988",
    "date_modified": "1418181170",
    "tags": "",
    "sourceId": "4",
    "VIDEO_LENGTH": "SHORT",
    "status": "approved",
    "visibility": "1",
    "id": "144450",
    "loginId": "521",
    "entityType": "1",
    "titleTextEncoded": "Zoo-Med-Tortoise-House",
    "category": null,
    "duration": 195,
    "settings": [],
    "asset": {
        "author": "Petco",
        "videoId": "RjvNe8rC8u4",
        "hookText": "http:\/\/video.petco.com\/?v=26346 View this video featuring the Zoo Med Tortoise House product and shop other similar products on petco.com. More information [...",
        "thumbnailUrl": "https:\/\/i.ytimg.com\/vi\/RjvNe8rC8u4\/maxresdefault.jpg",
        "mediaDuration": "195",
        "hdvFlag": 1,
        "uploadDate": 1331260686,
        "prettyDuration": "03:15"
    },
    "transcripts": null,
    "VV_VI": null,
    "CVV_VI": null,
    "engagement_score": null,
    "conversion_score": null,
    "metrics_statistics": null,
    "tvp_profiles": [
        "18"
    ],
    "tvp_profiles_manual": null,
    "tvp_profiles_maxscore": 474.49786
}