{
    "title": "Pet Tricks: Rizzo vs. Lizard",
    "description": "Subscribe to our channel: http:\/\/bit.ly\/12dY9oO Like us on Facebook: http:\/\/on.fb.me\/1cVLWAZ Follow us on Twitter: http:\/\/bit.ly\/1cVMcjn Check us out on Pint...",
    "referenceId": null,
    "date_created": "1394588978",
    "date_modified": "1418181169",
    "tags": "",
    "sourceId": "4",
    "VIDEO_LENGTH": "SHORT",
    "status": "approved",
    "visibility": "1",
    "id": "144360",
    "loginId": "521",
    "entityType": "1",
    "titleTextEncoded": "Pet-Tricks-Rizzo-vs-Lizard",
    "category": null,
    "duration": 16,
    "settings": [],
    "asset": {
        "author": "Petco",
        "videoId": "1hSXhutQW98",
        "hookText": "Subscribe to our channel: http:\/\/bit.ly\/12dY9oO Like us on Facebook: http:\/\/on.fb.me\/1cVLWAZ Follow us on Twitter: http:\/\/bit.ly\/1cVMcjn Check us out on Pint...",
        "thumbnailUrl": "https:\/\/i.ytimg.com\/vi\/1hSXhutQW98\/maxresdefault.jpg",
        "mediaDuration": "16",
        "hdvFlag": 1,
        "uploadDate": 1348625130,
        "prettyDuration": "00:16"
    },
    "transcripts": null,
    "VV_VI": null,
    "CVV_VI": null,
    "engagement_score": null,
    "conversion_score": null,
    "metrics_statistics": null,
    "tvp_profiles": [
        "18",
        "14",
        "7"
    ],
    "tvp_profiles_manual": null,
    "tvp_profiles_maxscore": 544.47314
}