{
    "title": "Nature's Miracle Product Ingredients",
    "description": "Learn the difference between the Nature's Miracle products and select the right one for you. [1] Buy Now - Nature's Miracle Stain & Odor Remover http:\/\/www.p...",
    "referenceId": null,
    "date_created": "1394588998",
    "date_modified": "1418181172",
    "tags": "",
    "sourceId": "4",
    "VIDEO_LENGTH": "SHORT",
    "status": "approved",
    "visibility": "1",
    "id": "144547",
    "loginId": "521",
    "entityType": "1",
    "titleTextEncoded": "Nature-s-Miracle-Product-Ingredients",
    "category": null,
    "duration": 139,
    "settings": [],
    "asset": {
        "author": "Petco",
        "videoId": "k9ggekRouSI",
        "hookText": "Learn the difference between the Nature's Miracle products and select the right one for you. [1] Buy Now - Nature's Miracle Stain & Odor Remover http:\/\/www.p...",
        "thumbnailUrl": "https:\/\/i.ytimg.com\/vi\/k9ggekRouSI\/maxresdefault.jpg",
        "mediaDuration": "139",
        "hdvFlag": 1,
        "uploadDate": 1317865040,
        "prettyDuration": "02:19"
    },
    "transcripts": null,
    "VV_VI": null,
    "CVV_VI": null,
    "engagement_score": null,
    "conversion_score": null,
    "metrics_statistics": null,
    "tvp_profiles": [
        "18",
        "12"
    ],
    "tvp_profiles_manual": null,
    "tvp_profiles_maxscore": 419.0305
}