{
    "title": "Trixie Activity Chess Dog Toy",
    "description": "http:\/\/video.petco.com\/?v=26920 View this video featuring the Trixie Activity Chess Dog Toy product and shop other similar products on petco.com. More inform...",
    "referenceId": null,
    "date_created": "1394588987",
    "date_modified": "1418181170",
    "tags": "",
    "sourceId": "4",
    "VIDEO_LENGTH": "SHORT",
    "status": "approved",
    "visibility": "1",
    "id": "144443",
    "loginId": "521",
    "entityType": "1",
    "titleTextEncoded": "Trixie-Activity-Chess-Dog-Toy",
    "category": null,
    "duration": 72,
    "settings": [],
    "asset": {
        "author": "Petco",
        "videoId": "ZwkTH0WvRXQ",
        "hookText": "http:\/\/video.petco.com\/?v=26920 View this video featuring the Trixie Activity Chess Dog Toy product and shop other similar products on petco.com. More inform...",
        "thumbnailUrl": "https:\/\/i.ytimg.com\/vi\/ZwkTH0WvRXQ\/maxresdefault.jpg",
        "mediaDuration": "72",
        "hdvFlag": 1,
        "uploadDate": 1331999752,
        "prettyDuration": "01:12"
    },
    "transcripts": null,
    "VV_VI": null,
    "CVV_VI": null,
    "engagement_score": null,
    "conversion_score": null,
    "metrics_statistics": null,
    "tvp_profiles": [
        "18"
    ],
    "tvp_profiles_manual": null,
    "tvp_profiles_maxscore": 445.4669
}