{
    "title": "Teach Your Dog to Sit: Petco How-To",
    "description": "Subscribe to our channel: http:\/\/bit.ly\/12dY9oO Train your dog with Petco! http:\/\/www.petco.com\/dogtraining Watch this informative video by Petco Animal Beha...",
    "referenceId": null,
    "date_created": "1394588963",
    "date_modified": "1418181168",
    "tags": "",
    "sourceId": "4",
    "VIDEO_LENGTH": "SHORT",
    "status": "approved",
    "visibility": "1",
    "id": "144218",
    "loginId": "521",
    "entityType": "1",
    "titleTextEncoded": "Teach-Your-Dog-to-Sit-Petco-How-To",
    "category": null,
    "duration": 70,
    "settings": [],
    "asset": {
        "author": "Petco",
        "videoId": "2rHHl0-Zpqg",
        "hookText": "Subscribe to our channel: http:\/\/bit.ly\/12dY9oO Train your dog with Petco! http:\/\/www.petco.com\/dogtraining Watch this informative video by Petco Animal Beha...",
        "thumbnailUrl": "https:\/\/i.ytimg.com\/vi\/2rHHl0-Zpqg\/maxresdefault.jpg",
        "mediaDuration": "70",
        "hdvFlag": 1,
        "uploadDate": 1388710804,
        "prettyDuration": "01:10"
    },
    "transcripts": null,
    "VV_VI": null,
    "CVV_VI": null,
    "engagement_score": null,
    "conversion_score": null,
    "metrics_statistics": null,
    "tvp_profiles": [
        "25",
        "7"
    ],
    "tvp_profiles_manual": null,
    "tvp_profiles_maxscore": 5706.347
}