{
    "title": "The Greatest Family Tree - Petco Great Ones Contest Finalist",
    "description": "Sorry, this contest has ended, but you can still subscribe to our channel for future ones. Subscribe to our channel: http:\/\/bit.ly\/12dY9oO Check this playlis...",
    "referenceId": null,
    "date_created": "1394818887",
    "date_modified": "1418181187",
    "tags": "",
    "sourceId": "4",
    "VIDEO_LENGTH": "SHORT",
    "status": "approved",
    "visibility": "1",
    "id": "145695",
    "loginId": "521",
    "entityType": "1",
    "titleTextEncoded": "The-Greatest-Family-Tree-Petco-Great-Ones-Contest-Finalist",
    "category": null,
    "duration": 211,
    "settings": [],
    "asset": {
        "author": "Petco",
        "videoId": "GF2Nk65Q6kU",
        "hookText": "Sorry, this contest has ended, but you can still subscribe to our channel for future ones. Subscribe to our channel: http:\/\/bit.ly\/12dY9oO Check this playlis...",
        "thumbnailUrl": "https:\/\/i.ytimg.com\/vi\/GF2Nk65Q6kU\/hqdefault.jpg",
        "mediaDuration": "211",
        "hdvFlag": 0,
        "uploadDate": 1377909556,
        "prettyDuration": "03:31"
    },
    "transcripts": null,
    "VV_VI": null,
    "CVV_VI": null,
    "engagement_score": null,
    "conversion_score": null,
    "metrics_statistics": null,
    "tvp_profiles": [
        "25",
        "32",
        "14"
    ],
    "tvp_profiles_manual": null,
    "tvp_profiles_maxscore": 378.95895
}