{
    "title": "We Need Love",
    "description": "The 4th installment of the JUST 2 GUYZ saga! Watch em all http:\/\/bit.ly\/1a0bcnQ or download: iTunes [w\/vid]: http:\/\/bit.ly\/13w2sxX iTunes [audio only]: http:...",
    "referenceId": null,
    "date_created": "1396559861",
    "date_modified": "1418181244",
    "tags": "",
    "sourceId": "4",
    "VIDEO_LENGTH": "SHORT",
    "status": "approved",
    "visibility": "1",
    "id": "149789",
    "loginId": "521",
    "entityType": "1",
    "titleTextEncoded": "We-Need-Love",
    "category": null,
    "duration": 162,
    "settings": [],
    "asset": {
        "author": "thelonelyisland",
        "videoId": "99swvqcCLb0",
        "hookText": "The 4th installment of the JUST 2 GUYZ saga! Watch em all http:\/\/bit.ly\/1a0bcnQ or download: iTunes [w\/vid]: http:\/\/bit.ly\/13w2sxX iTunes [audio only]: http:...",
        "thumbnailUrl": "https:\/\/i.ytimg.com\/vi\/99swvqcCLb0\/maxresdefault.jpg",
        "mediaDuration": "162",
        "hdvFlag": 1,
        "uploadDate": 1372928614,
        "prettyDuration": "02:42"
    },
    "transcripts": null,
    "VV_VI": null,
    "CVV_VI": null,
    "engagement_score": null,
    "conversion_score": null,
    "metrics_statistics": null,
    "tvp_profiles": [
        "32",
        "19",
        "31"
    ],
    "tvp_profiles_manual": null,
    "tvp_profiles_maxscore": 216.7314
}