{
    "title": "Legend Scot Schmidt - Salomon Freeski TV S7 E12",
    "description": "Scot Schmidt is a legend in Freeskiing. He is the original pro freeskier and became a household name in skiing after the release of the 1987 ski film, 'Blizz...",
    "referenceId": null,
    "date_created": "1403740415",
    "date_modified": "1418181688",
    "tags": "",
    "sourceId": "4",
    "VIDEO_LENGTH": "LONG",
    "status": "approved",
    "visibility": "1",
    "id": "185635",
    "loginId": "521",
    "entityType": "1",
    "titleTextEncoded": "Legend-Scot-Schmidt-Salomon-Freeski-TV-S7-E12",
    "category": null,
    "duration": 406,
    "settings": [],
    "asset": {
        "author": "salomonfreeskiTV",
        "hdvFlag": 1,
        "hookText": "Scot Schmidt is a legend in Freeskiing. He is the original pro freeskier and became a household name in skiing after the release of the 1987 ski film, 'Blizz...",
        "tags": "",
        "thumbnailUrl": "https:\/\/i.ytimg.com\/vi\/pPZ1oLBvkAg\/maxresdefault.jpg",
        "uploadDate": 1396360818,
        "videoId": "pPZ1oLBvkAg",
        "mediaDuration": "406",
        "prettyDuration": "06:46"
    },
    "transcripts": null,
    "VV_VI": null,
    "CVV_VI": null,
    "engagement_score": null,
    "conversion_score": null,
    "metrics_statistics": null,
    "tvp_profiles": [
        "8",
        "2",
        "9"
    ],
    "tvp_profiles_manual": null,
    "tvp_profiles_maxscore": 289.8117
}