{
    "title": "Spring Break - Salomon Freeski TV S7 E11",
    "description": "Sometimes things do not go as planned and you end up on Spring Break in the mountains with Josh Dueck, Cody Townsend, Josh Daiek & Leah Evans! Music: 'Countr...",
    "referenceId": null,
    "date_created": "1403742029",
    "date_modified": "1418181688",
    "tags": "",
    "sourceId": "4",
    "VIDEO_LENGTH": "LONG",
    "status": "approved",
    "visibility": "1",
    "id": "185637",
    "loginId": "521",
    "entityType": "1",
    "titleTextEncoded": "Spring-Break-Salomon-Freeski-TV-S7-E11",
    "category": null,
    "duration": 283,
    "settings": [],
    "asset": {
        "author": "salomonfreeskiTV",
        "hdvFlag": 1,
        "hookText": "Sometimes things do not go as planned and you end up on Spring Break in the mountains with Josh Dueck, Cody Townsend, Josh Daiek & Leah Evans! Music: 'Countr...",
        "tags": "",
        "thumbnailUrl": "https:\/\/i.ytimg.com\/vi\/jUcPW6uU2fI\/sddefault.jpg",
        "uploadDate": 1395413738,
        "videoId": "jUcPW6uU2fI",
        "mediaDuration": "283",
        "prettyDuration": "04:43"
    },
    "transcripts": null,
    "VV_VI": null,
    "CVV_VI": null,
    "engagement_score": null,
    "conversion_score": null,
    "metrics_statistics": null,
    "tvp_profiles": [
        "19"
    ],
    "tvp_profiles_manual": null,
    "tvp_profiles_maxscore": 6869.0586
}