{
    "title": "SB Chronicles Vol. 2: Justin Brock In Focus",
    "description": "Nike SB pro Justin Brock speaks on his highly-anticipated next video part in SB Chronicles Vol. 2. \n\nNike SB's new full-length video The SB Chronicles Vol. 2 hits iTunes on December 10th.\n\nCheck out http:\/\/www.SBChronicles.com for more information.",
    "referenceId": null,
    "date_created": "1424454638",
    "date_modified": "1424454638",
    "tags": "",
    "sourceId": "4",
    "VIDEO_LENGTH": "SHORT",
    "status": "approved",
    "visibility": "1",
    "id": "3824637",
    "loginId": "521",
    "entityType": "1",
    "titleTextEncoded": "SB-Chronicles-Vol-2-Justin-Brock-In-Focus",
    "category": null,
    "duration": 104,
    "settings": null,
    "asset": {
        "type": "youtube",
        "author": "Nike",
        "videoId": "w6m1IReR7IU",
        "hookText": "Nike SB pro Justin Brock speaks on his highly-anticipated next video part in SB Chronicles Vol. 2. \n\nNike SB's new full-length video The SB Chronicles Vol. 2 hits iTunes on December 10th.\n\nCheck out http:\/\/www.SBChronicles.com for more information.",
        "thumbnailUrl": "https:\/\/i.ytimg.com\/vi\/w6m1IReR7IU\/maxresdefault.jpg",
        "mediaDuration": "104",
        "hdvFlag": 1,
        "uploadDate": 1383888665,
        "prettyDuration": "01:44"
    },
    "transcripts": null,
    "VV_VI": null,
    "CVV_VI": null,
    "engagement_score": null,
    "conversion_score": null,
    "metrics_statistics": null,
    "tvp_profiles": [
        "22"
    ],
    "tvp_profiles_manual": null,
    "tvp_profiles_maxscore": 7273.177
}