{
    "title": "NikeSoccer+ Presents Master Accuracy",
    "description": "Want to learn deadly shooting straight from the backroom of Serie A\u00b9s high-scoring machine? With the new Master Accuracy training program, Juventus will help...",
    "referenceId": null,
    "date_created": "1424454635",
    "date_modified": "1424454635",
    "tags": "",
    "sourceId": "4",
    "VIDEO_LENGTH": "SHORT",
    "status": "approved",
    "visibility": "1",
    "id": "3824607",
    "loginId": "521",
    "entityType": "1",
    "titleTextEncoded": "NikeSoccer-Presents-Master-Accuracy",
    "category": null,
    "duration": 63,
    "settings": null,
    "asset": {
        "type": "youtube",
        "author": "Nike",
        "videoId": "jqSiR42JAEE",
        "hookText": "Want to learn deadly shooting straight from the backroom of Serie A\u00b9s high-scoring machine? With the new Master Accuracy training program, Juventus will help...",
        "thumbnailUrl": "https:\/\/i.ytimg.com\/vi\/jqSiR42JAEE\/hqdefault.jpg",
        "mediaDuration": "63",
        "hdvFlag": 0,
        "uploadDate": 1265890657,
        "prettyDuration": "01:03"
    },
    "transcripts": null,
    "VV_VI": null,
    "CVV_VI": null,
    "engagement_score": null,
    "conversion_score": null,
    "metrics_statistics": null,
    "tvp_profiles": [
        "25",
        "18",
        "12"
    ],
    "tvp_profiles_manual": null,
    "tvp_profiles_maxscore": 334.77423
}